canonicalwebteam/__init__.py
canonicalwebteam/search/__init__.py
canonicalwebteam/search/models.py
canonicalwebteam/search/views.py
canonicalwebteam_search-2.1.2.dist-info/licenses/LICENSE
tests/__init__.py
tests/test_app.py
tests/fixtures/__init__.py
tests/fixtures/search_mock.py
canonicalwebteam_search-2.1.2.dist-info/METADATA
canonicalwebteam_search-2.1.2.dist-info/WHEEL
canonicalwebteam_search-2.1.2.dist-info/top_level.txt
canonicalwebteam_search-2.1.2.dist-info/RECORD
