Metadata-Version: 2.4
Name: canonicalwebteam.search
Version: 2.1.2
Summary: Flask extension to provide a search view for querying the webteam's Google Custom Search account
Home-page: https://github.com/canonical/canonicalwebteam.search
Author: Canonical webteam
Author-email: webteam@canonical.com
License-File: LICENSE
Requires-Dist: canonicalwebteam.flask-base>=2.0.0
Requires-Dist: user-agents>=2.0.0
Requires-Dist: Flask-Limiter>=3.8.0
Dynamic: author
Dynamic: author-email
Dynamic: description
Dynamic: description-content-type
Dynamic: home-page
Dynamic: license-file
Dynamic: requires-dist
Dynamic: summary
